redis_fifo_lock/README.md
redis_fifo_lock/__init__.py
redis_fifo_lock/async_gate.py
redis_fifo_lock/common.py
redis_fifo_lock/sync.py
redis_fifo_lock-0.1.2.dist-info/licenses/LICENSE
redis_fifo_lock-0.1.2.dist-info/METADATA
redis_fifo_lock-0.1.2.dist-info/WHEEL
redis_fifo_lock-0.1.2.dist-info/top_level.txt
redis_fifo_lock-0.1.2.dist-info/RECORD
