Metadata-Version: 2.4
Name: redis-fifo-lock
Version: 0.1.2
Summary: Distributed FIFO lock using Redis Streams with strict ordering and crash recovery
License-Expression: MIT
Project-URL: Homepage, https://github.com/gaussian/redis-fifo-lock
Project-URL: Issues, https://github.com/gaussian/redis-fifo-lock/issues
Requires-Python: >=3.10
License-File: LICENSE
Requires-Dist: redis[hiredis]>=7.1
Provides-Extra: test
Requires-Dist: pytest>=7.0.0; extra == "test"
Requires-Dist: pytest-asyncio>=0.21.0; extra == "test"
Dynamic: license-file
